{
  "annotations": {
    "list": [
      {
        "builtIn": 1,
        "datasource": {
          "type": "datasource",
          "uid": "grafana"
        },
        "enable": true,
        "hide": true,
        "iconColor": "rgba(0, 211, 255, 1)",
        "name": "Annotations & Alerts",
        "target": {
          "limit": 100,
          "matchAny": false,
          "tags": [],
          "type": "dashboard"
        },
        "type": "dashboard"
      }
    ]
  },
  "editable": true,
  "fiscalYearStartMonth": 0,
  "graphTooltip": 0,
  "id": 5166,
  "links": [
    {
      "asDropdown": true,
      "icon": "external link",
      "includeVars": true,
      "keepTime": true,
      "tags": [
        "默认大盘"
      ],
      "targetBlank": false,
      "title": "快速访问",
      "tooltip": "",
      "type": "dashboards",
      "url": ""
    }
  ],
  "liveNow": false,
  "panels": [
    {
      "datasource": {
        "type": "prometheus",
        "uid": "${ds}"
      },
      "fieldConfig": {
        "defaults": {
          "color": {
            "mode": "thresholds"
          },
          "mappings": [],
          "thresholds": {
            "mode": "absolute",
            "steps": [
              {
                "color": "light-blue",
                "value": null
              }
            ]
          }
        },
        "overrides": []
      },
      "gridPos": {
        "h": 7,
        "w": 6,
        "x": 0,
        "y": 0
      },
      "id": 4,
      "options": {
        "displayMode": "gradient",
        "minVizHeight": 10,
        "minVizWidth": 0,
        "orientation": "auto",
        "reduceOptions": {
          "calcs": [
            "lastNotNull"
          ],
          "fields": "",
          "values": false
        },
        "showUnfilled": true,
        "text": {}
      },
      "pluginVersion": "9.0.4",
      "targets": [
        {
          "datasource": {
            "type": "prometheus",
            "uid": "${ds}"
          },
          "exemplar": true,
          "expr": "avg(go_threads{app_name=~\"$app\",cluster=~\"$cluster\",pod=~\"$pod\"})",
          "interval": "",
          "legendFormat": "avg",
          "refId": "A"
        },
        {
          "datasource": {
            "type": "prometheus",
            "uid": "${ds}"
          },
          "exemplar": true,
          "expr": "max(go_threads{app_name=~\"$app\",cluster=~\"$cluster\",pod=~\"$pod\"})",
          "hide": false,
          "instant": true,
          "interval": "",
          "legendFormat": "max",
          "refId": "B"
        },
        {
          "datasource": {
            "type": "prometheus",
            "uid": "${ds}"
          },
          "exemplar": true,
          "expr": "min(go_threads{app_name=~\"$app\",cluster=~\"$cluster\",pod=~\"$pod\"})",
          "hide": false,
          "instant": true,
          "interval": "",
          "legendFormat": "min",
          "refId": "C"
        }
      ],
      "title": "线程使用量(当前值)",
      "type": "bargauge"
    },
    {
      "datasource": {
        "type": "prometheus",
        "uid": "${ds}"
      },
      "fieldConfig": {
        "defaults": {
          "color": {
            "mode": "palette-classic"
          },
          "custom": {
            "axisLabel": "",
            "axisPlacement": "auto",
            "barAlignment": 0,
            "drawStyle": "line",
            "fillOpacity": 0,
            "gradientMode": "none",
            "hideFrom": {
              "legend": false,
              "tooltip": false,
              "viz": false
            },
            "lineInterpolation": "linear",
            "lineStyle": {
              "fill": "solid"
            },
            "lineWidth": 1,
            "pointSize": 5,
            "scaleDistribution": {
              "type": "linear"
            },
            "showPoints": "auto",
            "spanNulls": false,
            "stacking": {
              "group": "A",
              "mode": "none"
            },
            "thresholdsStyle": {
              "mode": "off"
            }
          },
          "mappings": [],
          "thresholds": {
            "mode": "absolute",
            "steps": [
              {
                "color": "green",
                "value": null
              }
            ]
          }
        },
        "overrides": []
      },
      "gridPos": {
        "h": 7,
        "w": 6,
        "x": 6,
        "y": 0
      },
      "id": 8,
      "options": {
        "legend": {
          "calcs": [],
          "displayMode": "list",
          "placement": "bottom"
        },
        "tooltip": {
          "mode": "single",
          "sort": "none"
        }
      },
      "targets": [
        {
          "datasource": {
            "type": "prometheus",
            "uid": "${ds}"
          },
          "exemplar": true,
          "expr": "sum(go_threads{app_name=~\"$app\",cluster=~\"$cluster\",pod=~\"$pod\"})",
          "format": "time_series",
          "hide": true,
          "instant": false,
          "interval": "",
          "legendFormat": "sum(go_threads)",
          "refId": "A"
        },
        {
          "datasource": {
            "type": "prometheus",
            "uid": "${ds}"
          },
          "exemplar": true,
          "expr": "avg(go_threads{app_name=~\"$app\",cluster=~\"$cluster\",pod=~\"$pod\"})",
          "hide": false,
          "interval": "",
          "legendFormat": "avg(go_threads)",
          "refId": "B"
        },
        {
          "datasource": {
            "type": "prometheus",
            "uid": "${ds}"
          },
          "exemplar": true,
          "expr": "max(go_threads{app_name=~\"$app\",cluster=~\"$cluster\",pod=~\"$pod\"})",
          "hide": false,
          "interval": "",
          "legendFormat": "max(go_threads)",
          "refId": "C"
        },
        {
          "datasource": {
            "type": "prometheus",
            "uid": "${ds}"
          },
          "exemplar": true,
          "expr": "min(go_threads{app_name=~\"$app\",cluster=~\"$cluster\",pod=~\"$pod\"})",
          "hide": false,
          "interval": "",
          "legendFormat": "min(go_threads)",
          "refId": "D"
        }
      ],
      "title": "线程使用量(go_threads_used)",
      "type": "timeseries"
    },
    {
      "datasource": {
        "type": "prometheus",
        "uid": "${ds}"
      },
      "fieldConfig": {
        "defaults": {
          "color": {
            "mode": "thresholds"
          },
          "mappings": [],
          "thresholds": {
            "mode": "absolute",
            "steps": [
              {
                "color": "light-blue",
                "value": null
              }
            ]
          }
        },
        "overrides": []
      },
      "gridPos": {
        "h": 7,
        "w": 6,
        "x": 12,
        "y": 0
      },
      "id": 100,
      "options": {
        "displayMode": "gradient",
        "minVizHeight": 10,
        "minVizWidth": 0,
        "orientation": "auto",
        "reduceOptions": {
          "calcs": [
            "lastNotNull"
          ],
          "fields": "",
          "values": false
        },
        "showUnfilled": true,
        "text": {}
      },
      "pluginVersion": "9.0.4",
      "targets": [
        {
          "datasource": {
            "type": "prometheus",
            "uid": "${ds}"
          },
          "exemplar": true,
          "expr": "avg(go_goroutines{app_name=~\"$app\",cluster=~\"$cluster\",pod=~\"$pod\"})",
          "instant": false,
          "interval": "",
          "legendFormat": "avg",
          "refId": "A"
        },
        {
          "datasource": {
            "type": "prometheus",
            "uid": "${ds}"
          },
          "exemplar": true,
          "expr": "max(go_goroutines{app_name=~\"$app\",cluster=~\"$cluster\",pod=~\"$pod\"})",
          "hide": false,
          "instant": false,
          "interval": "",
          "legendFormat": "max",
          "refId": "B"
        },
        {
          "datasource": {
            "type": "prometheus",
            "uid": "${ds}"
          },
          "exemplar": true,
          "expr": "min(go_goroutines{app_name=~\"$app\",cluster=~\"$cluster\",pod=~\"$pod\"})",
          "hide": false,
          "instant": false,
          "interval": "",
          "legendFormat": "min",
          "refId": "C"
        }
      ],
      "title": "协程使用量(当前值)",
      "type": "bargauge"
    },
    {
      "datasource": {
        "type": "prometheus",
        "uid": "${ds}"
      },
      "fieldConfig": {
        "defaults": {
          "color": {
            "mode": "palette-classic"
          },
          "custom": {
            "axisLabel": "",
            "axisPlacement": "auto",
            "barAlignment": 0,
            "drawStyle": "line",
            "fillOpacity": 0,
            "gradientMode": "none",
            "hideFrom": {
              "legend": false,
              "tooltip": false,
              "viz": false
            },
            "lineInterpolation": "smooth",
            "lineWidth": 1,
            "pointSize": 5,
            "scaleDistribution": {
              "type": "linear"
            },
            "showPoints": "auto",
            "spanNulls": false,
            "stacking": {
              "group": "A",
              "mode": "none"
            },
            "thresholdsStyle": {
              "mode": "off"
            }
          },
          "mappings": [],
          "thresholds": {
            "mode": "absolute",
            "steps": [
              {
                "color": "green",
                "value": null
              },
              {
                "color": "red",
                "value": 80
              }
            ]
          }
        },
        "overrides": []
      },
      "gridPos": {
        "h": 7,
        "w": 6,
        "x": 18,
        "y": 0
      },
      "id": 96,
      "options": {
        "legend": {
          "calcs": [],
          "displayMode": "list",
          "placement": "bottom"
        },
        "tooltip": {
          "mode": "single",
          "sort": "none"
        }
      },
      "targets": [
        {
          "datasource": {
            "type": "prometheus",
            "uid": "${ds}"
          },
          "exemplar": true,
          "expr": "max(go_goroutines{app_name=~\"$app\",cluster=~\"$cluster\",pod=~\"$pod\"})",
          "hide": false,
          "interval": "",
          "legendFormat": "max(go_goroutines)",
          "refId": "B"
        },
        {
          "datasource": {
            "type": "prometheus",
            "uid": "${ds}"
          },
          "exemplar": true,
          "expr": "avg(go_goroutines{app_name=~\"$app\",cluster=~\"$cluster\",pod=~\"$pod\"})",
          "hide": false,
          "interval": "",
          "legendFormat": "avg(go_goroutines)",
          "refId": "C"
        },
        {
          "datasource": {
            "type": "prometheus",
            "uid": "${ds}"
          },
          "exemplar": true,
          "expr": "min(go_goroutines{app_name=~\"$app\",cluster=~\"$cluster\",pod=~\"$pod\"})",
          "hide": false,
          "interval": "",
          "legendFormat": "min(go_goroutines)",
          "refId": "D"
        }
      ],
      "title": "协程使用量(go_goroutines_used)",
      "type": "timeseries"
    },
    {
      "datasource": {
        "type": "prometheus",
        "uid": "${ds}"
      },
      "fieldConfig": {
        "defaults": {
          "color": {
            "mode": "palette-classic"
          },
          "custom": {
            "axisLabel": "",
            "axisPlacement": "auto",
            "barAlignment": 0,
            "drawStyle": "line",
            "fillOpacity": 0,
            "gradientMode": "none",
            "hideFrom": {
              "legend": false,
              "tooltip": false,
              "viz": false
            },
            "lineInterpolation": "linear",
            "lineWidth": 1,
            "pointSize": 5,
            "scaleDistribution": {
              "type": "linear"
            },
            "showPoints": "auto",
            "spanNulls": false,
            "stacking": {
              "group": "A",
              "mode": "none"
            },
            "thresholdsStyle": {
              "mode": "off"
            }
          },
          "mappings": [],
          "thresholds": {
            "mode": "absolute",
            "steps": [
              {
                "color": "light-blue",
                "value": null
              },
              {
                "color": "red",
                "value": 80
              }
            ]
          }
        },
        "overrides": []
      },
      "gridPos": {
        "h": 8,
        "w": 12,
        "x": 0,
        "y": 7
      },
      "id": 104,
      "options": {
        "legend": {
          "calcs": [],
          "displayMode": "list",
          "placement": "bottom"
        },
        "tooltip": {
          "mode": "single",
          "sort": "none"
        }
      },
      "targets": [
        {
          "datasource": {
            "type": "prometheus",
            "uid": "${ds}"
          },
          "exemplar": true,
          "expr": "sum(process_open_fds{app_name=~\"$app\",cluster=~\"$cluster\",pod=~\"$pod\"}) by (pod)",
          "interval": "",
          "legendFormat": "",
          "refId": "A"
        }
      ],
      "title": "process_open_fds(打开的文件描述符的数量)",
      "type": "timeseries"
    },
    {
      "datasource": {
        "type": "prometheus",
        "uid": "${ds}"
      },
      "fieldConfig": {
        "defaults": {
          "color": {
            "mode": "palette-classic"
          },
          "custom": {
            "axisLabel": "",
            "axisPlacement": "auto",
            "barAlignment": 0,
            "drawStyle": "line",
            "fillOpacity": 0,
            "gradientMode": "none",
            "hideFrom": {
              "legend": false,
              "tooltip": false,
              "viz": false
            },
            "lineInterpolation": "smooth",
            "lineWidth": 1,
            "pointSize": 5,
            "scaleDistribution": {
              "type": "linear"
            },
            "showPoints": "auto",
            "spanNulls": false,
            "stacking": {
              "group": "A",
              "mode": "none"
            },
            "thresholdsStyle": {
              "mode": "off"
            }
          },
          "mappings": [],
          "thresholds": {
            "mode": "absolute",
            "steps": [
              {
                "color": "light-blue",
                "value": null
              },
              {
                "color": "red",
                "value": 80
              }
            ]
          },
          "unit": "core"
        },
        "overrides": []
      },
      "gridPos": {
        "h": 8,
        "w": 12,
        "x": 12,
        "y": 7
      },
      "id": 68,
      "options": {
        "legend": {
          "calcs": [],
          "displayMode": "list",
          "placement": "bottom"
        },
        "tooltip": {
          "mode": "single",
          "sort": "none"
        }
      },
      "targets": [
        {
          "datasource": {
            "type": "prometheus",
            "uid": "${ds}"
          },
          "exemplar": true,
          "expr": "sum(rate(process_cpu_seconds_total{app_name=~\"$app\",cluster=~\"$cluster\",pod=~\"$pod\"}[$__rate_interval])) by (pod)",
          "interval": "",
          "legendFormat": "",
          "refId": "A"
        }
      ],
      "title": "process_cpu_seconds_total(进程使用CPU核数)",
      "type": "timeseries"
    },
    {
      "datasource": {
        "type": "prometheus",
        "uid": "${ds}"
      },
      "description": "",
      "fieldConfig": {
        "defaults": {
          "color": {
            "mode": "palette-classic"
          },
          "custom": {
            "axisLabel": "",
            "axisPlacement": "auto",
            "barAlignment": 0,
            "drawStyle": "line",
            "fillOpacity": 0,
            "gradientMode": "none",
            "hideFrom": {
              "legend": false,
              "tooltip": false,
              "viz": false
            },
            "lineInterpolation": "linear",
            "lineWidth": 1,
            "pointSize": 5,
            "scaleDistribution": {
              "type": "linear"
            },
            "showPoints": "auto",
            "spanNulls": false,
            "stacking": {
              "group": "A",
              "mode": "none"
            },
            "thresholdsStyle": {
              "mode": "off"
            }
          },
          "mappings": [],
          "thresholds": {
            "mode": "absolute",
            "steps": [
              {
                "color": "light-blue",
                "value": null
              },
              {
                "color": "red",
                "value": 80
              }
            ]
          },
          "unit": "gbytes"
        },
        "overrides": []
      },
      "gridPos": {
        "h": 8,
        "w": 12,
        "x": 0,
        "y": 15
      },
      "id": 106,
      "options": {
        "legend": {
          "calcs": [],
          "displayMode": "list",
          "placement": "bottom"
        },
        "tooltip": {
          "mode": "single",
          "sort": "none"
        }
      },
      "targets": [
        {
          "datasource": {
            "type": "prometheus",
            "uid": "${ds}"
          },
          "exemplar": true,
          "expr": "sum(process_virtual_memory_bytes{app_name=~\"$app\",cluster=~\"$cluster\",pod=~\"$pod\"}) by (pod) /1024 /1024 /1024",
          "interval": "",
          "legendFormat": "",
          "refId": "A"
        }
      ],
      "title": "process_virtual_memory_bytes(虚拟内存大小)",
      "type": "timeseries"
    },
    {
      "datasource": {
        "type": "prometheus",
        "uid": "${ds}"
      },
      "description": "",
      "fieldConfig": {
        "defaults": {
          "color": {
            "mode": "palette-classic"
          },
          "custom": {
            "axisLabel": "",
            "axisPlacement": "auto",
            "barAlignment": 0,
            "drawStyle": "line",
            "fillOpacity": 0,
            "gradientMode": "none",
            "hideFrom": {
              "legend": false,
              "tooltip": false,
              "viz": false
            },
            "lineInterpolation": "smooth",
            "lineWidth": 1,
            "pointSize": 5,
            "scaleDistribution": {
              "type": "linear"
            },
            "showPoints": "auto",
            "spanNulls": false,
            "stacking": {
              "group": "A",
              "mode": "none"
            },
            "thresholdsStyle": {
              "mode": "off"
            }
          },
          "mappings": [],
          "thresholds": {
            "mode": "absolute",
            "steps": [
              {
                "color": "light-blue",
                "value": null
              },
              {
                "color": "red",
                "value": 80
              }
            ]
          },
          "unit": "mbytes"
        },
        "overrides": []
      },
      "gridPos": {
        "h": 8,
        "w": 12,
        "x": 12,
        "y": 15
      },
      "id": 76,
      "options": {
        "legend": {
          "calcs": [],
          "displayMode": "list",
          "placement": "bottom"
        },
        "tooltip": {
          "mode": "single",
          "sort": "none"
        }
      },
      "targets": [
        {
          "datasource": {
            "type": "prometheus",
            "uid": "${ds}"
          },
          "exemplar": true,
          "expr": "sum(process_resident_memory_bytes{app_name=~\"$app\",cluster=~\"$cluster\",pod=~\"$pod\"}) by (pod) /1024 /1024 ",
          "interval": "",
          "legendFormat": "",
          "refId": "A"
        }
      ],
      "title": "process_resident_memory_bytes(进程常驻内存大小)",
      "type": "timeseries"
    },
    {
      "datasource": {
        "type": "prometheus",
        "uid": "${ds}"
      },
      "fieldConfig": {
        "defaults": {
          "color": {
            "mode": "palette-classic"
          },
          "custom": {
            "axisLabel": "",
            "axisPlacement": "auto",
            "barAlignment": 0,
            "drawStyle": "line",
            "fillOpacity": 0,
            "gradientMode": "none",
            "hideFrom": {
              "legend": false,
              "tooltip": false,
              "viz": false
            },
            "lineInterpolation": "smooth",
            "lineWidth": 1,
            "pointSize": 5,
            "scaleDistribution": {
              "type": "linear"
            },
            "showPoints": "auto",
            "spanNulls": false,
            "stacking": {
              "group": "A",
              "mode": "none"
            },
            "thresholdsStyle": {
              "mode": "off"
            }
          },
          "mappings": [],
          "thresholds": {
            "mode": "absolute",
            "steps": [
              {
                "color": "light-blue",
                "value": null
              },
              {
                "color": "red",
                "value": 80
              }
            ]
          },
          "unit": "s"
        },
        "overrides": []
      },
      "gridPos": {
        "h": 8,
        "w": 12,
        "x": 0,
        "y": 23
      },
      "id": 18,
      "options": {
        "legend": {
          "calcs": [],
          "displayMode": "list",
          "placement": "bottom"
        },
        "tooltip": {
          "mode": "single",
          "sort": "none"
        }
      },
      "targets": [
        {
          "datasource": {
            "type": "prometheus",
            "uid": "${ds}"
          },
          "exemplar": true,
          "expr": "sum(increase(go_gc_duration_seconds_sum{app_name=~\"$app\",cluster=~\"$cluster\",pod=~\"$pod\"}[$__interval])) by (pod)",
          "interval": "",
          "legendFormat": "",
          "refId": "A"
        }
      ],
      "title": "go_gc_duration_seconds_sum(GC STW 时间)",
      "type": "timeseries"
    },
    {
      "datasource": {
        "type": "prometheus",
        "uid": "${ds}"
      },
      "fieldConfig": {
        "defaults": {
          "color": {
            "mode": "palette-classic"
          },
          "custom": {
            "axisLabel": "",
            "axisPlacement": "auto",
            "barAlignment": 0,
            "drawStyle": "line",
            "fillOpacity": 0,
            "gradientMode": "none",
            "hideFrom": {
              "legend": false,
              "tooltip": false,
              "viz": false
            },
            "lineInterpolation": "linear",
            "lineWidth": 1,
            "pointSize": 5,
            "scaleDistribution": {
              "type": "linear"
            },
            "showPoints": "auto",
            "spanNulls": false,
            "stacking": {
              "group": "A",
              "mode": "none"
            },
            "thresholdsStyle": {
              "mode": "off"
            }
          },
          "mappings": [],
          "thresholds": {
            "mode": "absolute",
            "steps": [
              {
                "color": "light-blue",
                "value": null
              },
              {
                "color": "red",
                "value": 80
              }
            ]
          }
        },
        "overrides": []
      },
      "gridPos": {
        "h": 8,
        "w": 12,
        "x": 12,
        "y": 23
      },
      "id": 12,
      "options": {
        "legend": {
          "calcs": [],
          "displayMode": "list",
          "placement": "bottom"
        },
        "tooltip": {
          "mode": "single",
          "sort": "none"
        }
      },
      "targets": [
        {
          "datasource": {
            "type": "prometheus",
            "uid": "${ds}"
          },
          "exemplar": true,
          "expr": "sum(increase(go_gc_duration_seconds_count{app_name=~\"$app\",cluster=~\"$cluster\",pod=~\"$pod\"}[$__interval])) by (pod)",
          "interval": "",
          "legendFormat": "",
          "refId": "A"
        }
      ],
      "title": "go_gc_duration_seconds_count(GC STW 次数)",
      "type": "timeseries"
    },
    {
      "datasource": {
        "type": "prometheus",
        "uid": "${ds}"
      },
      "fieldConfig": {
        "defaults": {
          "color": {
            "mode": "palette-classic"
          },
          "custom": {
            "axisLabel": "",
            "axisPlacement": "auto",
            "barAlignment": 0,
            "drawStyle": "line",
            "fillOpacity": 1,
            "gradientMode": "none",
            "hideFrom": {
              "legend": false,
              "tooltip": false,
              "viz": false
            },
            "lineInterpolation": "smooth",
            "lineWidth": 1,
            "pointSize": 5,
            "scaleDistribution": {
              "type": "linear"
            },
            "showPoints": "auto",
            "spanNulls": false,
            "stacking": {
              "group": "A",
              "mode": "none"
            },
            "thresholdsStyle": {
              "mode": "off"
            }
          },
          "mappings": [],
          "thresholds": {
            "mode": "absolute",
            "steps": [
              {
                "color": "light-blue",
                "value": null
              },
              {
                "color": "red",
                "value": 80
              }
            ]
          },
          "unit": "mbytes"
        },
        "overrides": []
      },
      "gridPos": {
        "h": 8,
        "w": 12,
        "x": 0,
        "y": 31
      },
      "id": 20,
      "options": {
        "legend": {
          "calcs": [],
          "displayMode": "list",
          "placement": "bottom"
        },
        "tooltip": {
          "mode": "single",
          "sort": "none"
        }
      },
      "targets": [
        {
          "datasource": {
            "type": "prometheus",
            "uid": "${ds}"
          },
          "exemplar": true,
          "expr": "sum(increase(go_memstats_alloc_bytes_total{app_name=~\"$app\",cluster=~\"$cluster\",pod=~\"$pod\"}[$__interval])) by (pod)/1024 /1024 ",
          "interval": "",
          "legendFormat": "",
          "refId": "A"
        }
      ],
      "title": " go_memstats_alloc_bytes_total(分配内存大小)",
      "type": "timeseries"
    },
    {
      "datasource": {
        "type": "prometheus",
        "uid": "${ds}"
      },
      "description": "",
      "fieldConfig": {
        "defaults": {
          "color": {
            "mode": "thresholds"
          },
          "custom": {
            "align": "auto",
            "displayMode": "auto",
            "filterable": false,
            "inspect": false
          },
          "mappings": [],
          "thresholds": {
            "mode": "absolute",
            "steps": [
              {
                "color": "light-blue",
                "value": null
              }
            ]
          },
          "unit": "none"
        },
        "overrides": [
          {
            "matcher": {
              "id": "byRegexp",
              "options": "进程启动时间"
            },
            "properties": [
              {
                "id": "unit",
                "value": "dateTimeAsLocal"
              }
            ]
          }
        ]
      },
      "gridPos": {
        "h": 8,
        "w": 12,
        "x": 12,
        "y": 31
      },
      "id": 74,
      "options": {
        "footer": {
          "fields": "",
          "reducer": [
            "sum"
          ],
          "show": false
        },
        "showHeader": true,
        "sortBy": [
          {
            "desc": false,
            "displayName": "进程启动时间"
          }
        ]
      },
      "pluginVersion": "9.0.4",
      "targets": [
        {
          "datasource": {
            "type": "prometheus",
            "uid": "${ds}"
          },
          "exemplar": true,
          "expr": "process_start_time_seconds{app_name=~\"$app\",pod=~\"$pod\"} * 1000",
          "format": "table",
          "instant": true,
          "interval": "",
          "legendFormat": "",
          "refId": "A"
        }
      ],
      "title": "process_start_time_seconds(进程启动时间)",
      "transformations": [
        {
          "id": "organize",
          "options": {
            "excludeByName": {
              "Time": true,
              "Value": false,
              "__name__": true,
              "app_name": true,
              "cluster": true,
              "instance": true,
              "job": true,
              "kubernetes_namespace": true,
              "kubernetes_pod_name": true
            },
            "indexByName": {},
            "renameByName": {
              "Time": "",
              "Value": "进程启动时间",
              "Value #A": "进程启动unix时间戳",
              "app_name": "app",
              "pod": "pod"
            }
          }
        }
      ],
      "type": "table"
    },
    {
      "datasource": {
        "type": "prometheus",
        "uid": "${ds}"
      },
      "fieldConfig": {
        "defaults": {
          "color": {
            "mode": "thresholds"
          },
          "mappings": [],
          "thresholds": {
            "mode": "absolute",
            "steps": [
              {
                "color": "light-blue",
                "value": null
              },
              {
                "color": "red",
                "value": 80
              }
            ]
          }
        },
        "overrides": []
      },
      "gridPos": {
        "h": 8,
        "w": 5,
        "x": 0,
        "y": 39
      },
      "id": 183,
      "options": {
        "colorMode": "value",
        "graphMode": "area",
        "justifyMode": "auto",
        "orientation": "auto",
        "reduceOptions": {
          "calcs": [
            "lastNotNull"
          ],
          "fields": "",
          "values": false
        },
        "text": {},
        "textMode": "auto"
      },
      "pluginVersion": "9.0.4",
      "targets": [
        {
          "datasource": {
            "type": "prometheus",
            "uid": "${ds}"
          },
          "exemplar": true,
          "expr": "sum(increase(panic_recovered{app_name=~\"$app\",cluster=~\"$cluster\",pod=~\"$pod\"}[10s]))",
          "format": "time_series",
          "instant": false,
          "interval": "",
          "legendFormat": "",
          "refId": "A"
        }
      ],
      "title": "Panic信息(当前值)",
      "type": "stat"
    },
    {
      "datasource": {
        "type": "prometheus",
        "uid": "${ds}"
      },
      "fieldConfig": {
        "defaults": {
          "color": {
            "mode": "palette-classic"
          },
          "custom": {
            "axisLabel": "",
            "axisPlacement": "auto",
            "barAlignment": 0,
            "drawStyle": "line",
            "fillOpacity": 0,
            "gradientMode": "none",
            "hideFrom": {
              "legend": false,
              "tooltip": false,
              "viz": false
            },
            "lineInterpolation": "linear",
            "lineWidth": 1,
            "pointSize": 5,
            "scaleDistribution": {
              "type": "linear"
            },
            "showPoints": "auto",
            "spanNulls": false,
            "stacking": {
              "group": "A",
              "mode": "none"
            },
            "thresholdsStyle": {
              "mode": "off"
            }
          },
          "mappings": [],
          "thresholds": {
            "mode": "absolute",
            "steps": [
              {
                "color": "light-blue",
                "value": null
              }
            ]
          }
        },
        "overrides": [
          {
            "matcher": {
              "id": "byName",
              "options": "panic_recovered"
            },
            "properties": [
              {
                "id": "color",
                "value": {
                  "fixedColor": "light-blue",
                  "mode": "fixed"
                }
              }
            ]
          }
        ]
      },
      "gridPos": {
        "h": 8,
        "w": 19,
        "x": 5,
        "y": 39
      },
      "id": 108,
      "options": {
        "legend": {
          "calcs": [],
          "displayMode": "list",
          "placement": "bottom"
        },
        "tooltip": {
          "mode": "single",
          "sort": "none"
        }
      },
      "targets": [
        {
          "datasource": {
            "type": "prometheus",
            "uid": "${ds}"
          },
          "exemplar": true,
          "expr": "sum(increase(panic_recovered{app_name=~\"$app\",cluster=~\"$cluster\",pod=~\"$pod\"}[10s]))",
          "interval": "",
          "legendFormat": "panic_recovered",
          "refId": "A"
        }
      ],
      "title": "程序启动以来panic总数 panic_recovered",
      "type": "timeseries"
    }
  ],
  "refresh": "",
  "schemaVersion": 36,
  "style": "dark",
  "tags": [
    "GDP",
    "默认大盘"
  ],
  "templating": {
    "list": [
      {
        "current": {
          "selected": false,
          "text": "Prometheus监控",
          "value": "Prometheus监控"
        },
        "hide": 0,
        "includeAll": false,
        "label": "数据源",
        "multi": false,
        "name": "ds",
        "options": [],
        "query": "prometheus",
        "queryValue": "",
        "refresh": 1,
        "regex": "/^Prometheus/",
        "skipUrlSync": false,
        "type": "datasource"
      },
      {
        "current": {
          "selected": false,
          "text": "group.mapse-RecStorage-RecStorage.map-se.all",
          "value": "group.mapse-RecStorage-RecStorage.map-se.all"
        },
        "datasource": {
          "type": "prometheus",
          "uid": "${ds}"
        },
        "definition": "label_values(gdp_metrics_info,app_name)",
        "hide": 0,
        "includeAll": false,
        "multi": false,
        "name": "app",
        "options": [],
        "query": {
          "query": "label_values(gdp_metrics_info,app_name)",
          "refId": "StandardVariableQuery"
        },
        "refresh": 1,
        "regex": "",
        "skipUrlSync": false,
        "sort": 0,
        "type": "query"
      },
      {
        "current": {
          "selected": false,
          "text": "All",
          "value": "$__all"
        },
        "datasource": {
          "type": "prometheus",
          "uid": "${ds}"
        },
        "definition": "label_values(go_goroutines{app_name=~\"$app\"},cluster)",
        "hide": 0,
        "includeAll": true,
        "multi": false,
        "name": "cluster",
        "options": [],
        "query": {
          "query": "label_values(go_goroutines{app_name=~\"$app\"},cluster)",
          "refId": "StandardVariableQuery"
        },
        "refresh": 1,
        "regex": "",
        "skipUrlSync": false,
        "sort": 0,
        "type": "query"
      },
      {
        "current": {
          "selected": false,
          "text": "All",
          "value": "$__all"
        },
        "datasource": {
          "type": "prometheus",
          "uid": "${ds}"
        },
        "definition": "label_values(go_goroutines{app_name=~\"$app\",cluster=~\"$cluster\"},pod)",
        "hide": 0,
        "includeAll": true,
        "multi": false,
        "name": "pod",
        "options": [],
        "query": {
          "query": "label_values(go_goroutines{app_name=~\"$app\",cluster=~\"$cluster\"},pod)",
          "refId": "StandardVariableQuery"
        },
        "refresh": 1,
        "regex": "",
        "skipUrlSync": false,
        "sort": 0,
        "type": "query"
      }
    ]
  },
  "time": {
    "from": "now-5m",
    "to": "now"
  },
  "timepicker": {},
  "timezone": "",
  "title": "GDP框架监控",
  "uid": "prom_gdp_framework",
  "version": 6,
  "weekStart": ""
}